wfchef/__init__.py
wfchef/chef.py
wfchef/duplicate.py
wfchef/find_microstructures.py
wfchef/utils.py
wfchef-0.1.dist-info/METADATA
wfchef-0.1.dist-info/WHEEL
wfchef-0.1.dist-info/entry_points.txt
wfchef-0.1.dist-info/top_level.txt
wfchef-0.1.dist-info/RECORD
